AUTHORS
LICENSE
MANIFEST.in
README.rst
runtests.py
setup.py
django_modeltranslation_wrapper.egg-info/PKG-INFO
django_modeltranslation_wrapper.egg-info/SOURCES.txt
django_modeltranslation_wrapper.egg-info/dependency_links.txt
django_modeltranslation_wrapper.egg-info/requires.txt
django_modeltranslation_wrapper.egg-info/top_level.txt
modeltranslation_wrapper/__init__.py
modeltranslation_wrapper/manager.py
modeltranslation_wrapper/models.py
modeltranslation_wrapper/patch.py
modeltranslation_wrapper/translation_autodiscover.py
modeltranslation_wrapper/tests/__init__.py
modeltranslation_wrapper/tests/nothing.py
modeltranslation_wrapper/tests/project_translation.py
modeltranslation_wrapper/tests/settings.py
modeltranslation_wrapper/tests/test_app/__init__.py
modeltranslation_wrapper/tests/test_app/manager.py
modeltranslation_wrapper/tests/test_app/models.py
modeltranslation_wrapper/tests/test_app/translation.py