Metadata-Version: 1.1
Name: django-modeltranslation-wrapper
Version: 1.2.2
Summary: Wrapper around modeltranslation package, adding nice features.
Home-page: https://github.com/zlorf/django-modeltranslation-wrapper
Author: Jacek Tomaszewski
Author-email: jacek.tomek@gmail.com
License: BSD
Platform: UNKNOWN
Classifier: Development Status :: 5 - Production/Stable
Classifier: Environment :: Web Environment
Classifier: License :: OSI Approved :: BSD License
Classifier: Operating System :: OS Independent
Classifier: Programming Language :: Python
Classifier: Framework :: Django
